{"namePlayer":"Caio","namePJ":"Jake","agi":"2","for":"2","int":"2","pre":"2","vig":"1","origem":"Policial ","percepcao":"5","pontaria":"5","outrosDefesas":"2","passiva":"14","classe":"Especialista","nex":"5","pv":"17","pvSofrido":"17","pe":"5","sanPerdida":"5","san":"16","peGasto":"16","acrobacia":"5","iniciativa":"5","intimidacao":"5","intuicao":"5","invetigacao":"5","luta":"5","ocultismo":"5","tatica":"5","vontade":"5","proficiencias":"Armas simples e proteção leve","habilidades":[{"habilidadeName":"Eclético:","habilidadeDescri":"Quando faz um teste de uma\nperícia, você pode gastar 2 PE para receber\nos benefícios de ser treinado nesta perícia."},{"habilidadeName":"Perito:(acrobacias e ocultismo)","habilidadeDescri":"Escolha duas perícias nas quais você é treinado\n(exceto Luta e Pontaria). Quando faz um teste\nde uma dessas perícias, você pode gastar 2 PE para\nsomar +1d6 no resultado do teste. Conforme avança\nde NEX, você pode gastar +1 PE para aumentar o dado\nde bônus (veja a Tabela 1.4). Por exemplo, em NEX\n55%, pode gastar 4 PE para receber +1d12 no teste."}],"patente":"Recruta ","ptPrestigio":"0","liniteNivel1":"2","credito":"Baixo","mochilaAtual":"12","item1":"Mochila militar ","item2":"Lança ","item3":"Kit de perícia ","espacos3":"1","espacos2":"1","espacos1":"0","item4":"Pistola","espacos4":"1","prestigio2":"0","prestigio4":"1","prestigio1":"1","prestigio3":"0","item5":"Escudo","espacos5":"2","prestigio5":"0","item6":"Bala curta","espacos6":"2","detalhes6":"2 balas curtas","prestigio6":"0","item7":"Faca","prestigio7":"0","espacos7":"1","item8":"Lanterna","prestigio8":"0","espacos8":"1","mochilaTotal":"9"}